Metadata-Version: 2.1
Name: odoo14-addon-odoo-web-login
Version: 14.0.1.0.1.dev2
Summary: The new configurable Odoo Web Login Screen
Home-page: https://www.xaoxao.vn
Author: Xao Xao Digital CO.,LTD
License: AGPL-3
Platform: UNKNOWN
Classifier: Programming Language :: Python
Classifier: Framework :: Odoo
Classifier: Framework :: Odoo :: 14.0
Classifier: License :: OSI Approved :: GNU Affero General Public License v3
Requires-Python: >=3.6
Requires-Dist: odoo <14.1dev,>=14.0a
